junction_python-0.3.3.dist-info/METADATA
junction_python-0.3.3.dist-info/WHEEL
junction_python-0.3.3.dist-info/licenses/LICENSE
junction/urllib3.py
junction/config.py
junction/__init__.py
junction/requests.py
junction/junction.abi3.so
junction_python-0.3.3.dist-info/RECORD
