Metadata-Version: 2.4
Name: junction-python
Version: 0.3.3
Classifier: Development Status :: 3 - Alpha
Classifier: Programming Language :: Python
Classifier: Programming Language :: Python :: 3
Classifier: Programming Language :: Python :: 3 :: Only
Classifier: Programming Language :: Python :: 3.9
Classifier: Programming Language :: Python :: 3.10
Classifier: Programming Language :: Python :: 3.11
Classifier: Programming Language :: Python :: 3.12
Classifier: Programming Language :: Rust
Requires-Dist: requests>2.0
Requires-Dist: urllib3>2.0
Requires-Dist: pytest ; extra == 'test'
Provides-Extra: test
License-File: LICENSE
Summary: An embeddable, dynamically configurable HTTP library
Keywords: service discovery,http
Home-Page: https://junctionlabs.io
Author-email: Ben Linsay <blinsay@gmail.com>
License: Apache-2.0
Requires-Python: >=3.9
Project-URL: Homepage, https://junctionlabs.io
Project-URL: Repository, https://github.com/junction-labs/junction-client
